README.md
setup.py
tweetprep/DESCRIPTION.rst
tweetprep/__init__.py
tweetprep/preprocess.py
tweetprep.egg-info/PKG-INFO
tweetprep.egg-info/SOURCES.txt
tweetprep.egg-info/dependency_links.txt
tweetprep.egg-info/requires.txt
tweetprep.egg-info/top_level.txt