Metadata-Version: 1.1
Name: tweetprep
Version: 2.0.5
Summary: A small preprocessor for tweets.
Home-page: https://github.com/garain/tweetprep
Author: Avishek Garain
Author-email: avishekgarain@gmail.com
License: MIT
Keywords: tweet translate preprocess
Platform: UNKNOWN
Classifier: Development Status :: 4 - Beta
Classifier: Intended Audience :: Developers
Classifier: Topic :: Internet
Classifier: License :: OSI Approved :: MIT License
Classifier: Programming Language :: Python
Classifier: Programming Language :: Python :: 2
Classifier: Programming Language :: Python :: 2.6
Classifier: Programming Language :: Python :: 2.7
Classifier: Programming Language :: Python :: 3
Classifier: Programming Language :: Python :: 3.3
Classifier: Programming Language :: Python :: 3.4
Classifier: Programming Language :: Python :: 3.5
